{
  "audiovisual_files": {
    "239e33a6-f066-4dc8-84ea-25bfb410dd27": {
      "label": "Environment Texas Dr. Brooks Interview ",
      "is_offline": false,
      "file_type": "Video",
      "file_url": "https://youtu.be/C-5iQ_Xoc2c",
      "duration": 204
    }
  },
  "auto_generate_web_page": true,
  "label": "Environment Texas Dr. Brooks Interview ",
  "description": [
    {
      "type": "paragraph",
      "children": [
        {
          "text": "“Stories from the Oilfields” is our ongoing series of collected interviews from residents of some of the oil producing areas of Texas and experts on the impacts of the fossil fuel industry."
        }
      ]
    }
  ],
  "created_at": "2025-05-23T20:37:08.122Z",
  "created_by": "trentwintermeier",
  "updated_at": "2025-05-23T20:37:08.122Z",
  "updated_by": "trentwintermeier"
}